pulumi_external/__init__.py
pulumi_external/_utilities.py
pulumi_external/get_external.py
pulumi_external/provider.py
pulumi_external/pulumi-plugin.json
pulumi_external/py.typed
pulumi_external-0.0.17.dist-info/METADATA
pulumi_external-0.0.17.dist-info/WHEEL
pulumi_external-0.0.17.dist-info/top_level.txt
pulumi_external-0.0.17.dist-info/RECORD
